[{
    "img":"https://i.ibb.co/zffbzG2/21-WQCyvs-SML-AC-UF226-226-FMjpg.jpg",
    "title":"Fire TV Devices",
    "deal":"deal",
    "discount":"10"
  },
{
    "img":"https://i.ibb.co/0BPbfGC/31-Jh6teont-L-AC-UF226-226-FMjpg.jpg",
    "title":"Prime Members Save on Kindle Scribe",
    "deal":"deal",
    "discount":"9"
  },
{
    "img":"https://i.ibb.co/42LhjhD/31-T4-Ic-Ip-Yf-L-AC-UF226-226-FMjpg.jpg",
    "title":"Blink Smart Home Security Doorbells and Cameras",
    "deal":"deal",
    "discount":"11"
  }, 
 {
    "img":"https://i.ibb.co/C8dNz4D/5175wxb-LHLL-AC-UF226-226-FMjpg.jpg",
    "title":"Nugget Ice Makers Countertop, 33 Lbs/Day Sonic Ice Maker, Countertop Ice Maker with",
    "deal":"deal",
    "discount":"33"
 }, 
 {
    "img":"https://i.ibb.co/tMqF3My/4149-SRZHue-L-AC-UF226-226-FMjpg.jpg",
    "title":"Euhomy Appliances",
    "deal":"deal",
    "discount":"30"
 }, 
 {
    "img":"https://i.ibb.co/y6N2rS4/419qet-BVXTL-AC-UF226-226-FMjpg.jpg",
    "title":"Waterdrop LT1000PC ADQ747935 NSF 42 Refrigerator Water Filter and Air Filter",
    "deal":"deal",
    "discount":"39"
 }, 
 {
    "img":"https://i.ibb.co/0cCY5cK/415-JZb-KUix-L-AC-UF226-226-FMjpg.jpg",
    "title":"ICEPURE RWF4700AC Replacement for LG LT1000P MDJ64844601 ADQ74793501",
    "deal":"deal",
    "discount":"43"
 }, 
 {
    "img":"https://i.ibb.co/QDdxP8k/412-Uk-Jve-LIL-AC-UF226-226-FMjpg.jpg",
    "title":"Aeitto Cold Press Juicer Machines, 3.6 Inch Wide Chute, Large Capacity, High Juice Yield, 2 Masticating Juicer Modes, Easy to Clean Slow",
    "deal":"deal",
    "discount":"32"
 }, 
 {
    "img":"https://i.ibb.co/hghQhQN/317c-Xd-M3j-L-AC-UF226-226-FMjpg.jpg",
    "title":"Kismile Compact Upright Freezer with Reversible Single Door,Removable Shelves Mini",
    "deal":"deal",
    "discount":"34"
 }, 
 {
    "img":"https://i.ibb.co/gWd57D5/313-4rd-Ay2-L-AC-UF226-226-FMjpg.jpg",
    "title":"Filterlogic UKF8001 Replacement for EveryDrop Filter 4, Whirlpool EDR4RXD1, Maytag 4396395, UKF8001AXX-200, UKF8001AXX",
    "deal":"deal",
    "discount":"15"
 }, 
 {
    "img":"https://i.ibb.co/d6ZwmB0/312-Cc-OM9qs-L-AC-UF226-226-FMjpg.jpg",
    "title":"AGLUCKY Countertop Ice Maker Machine, Portable Ice Makers Countertop",
    "deal":"deal",
    "discount":"17"
 }, 
 {
    "img":"https://i.ibb.co/WtwdDfB/213p-WPs-DBs-L-AC-UF226-226-FMjpg.jpg",
    "title":"ICEPURE UKF8001 Compatible with Whirlpool EDR4RXD1, 4396395, Maytag UKF8001,",
    "deal":"deal",
    "discount":"19"
 }, 
 {
    "img":"https://i.ibb.co/wwVp14S/51c-Qhu-v-A8-L-AC-UF226-226-FMjpg.jpg",
    "title":"Silonn Ice Maker Countertop, 9 Cubes Ready in 6 Mins, 26lbs in 24Hrs, Self-Cleaning Ice",
    "deal":"deal",
    "discount":"33"
 }, 
 {
    "img":"https://i.ibb.co/cb4LVT8/41-Z-KAMW3-L-AC-UF226-226-FMjpg.jpg",
    "title":"Midea & Comfee Laundry Appliances",
    "deal":"deal",
    "discount":"18"
 }, 
 {
    "img":"https://i.ibb.co/MSJb75p/41-YRo-JAdi-QL-AC-UF226-226-FMjpg.jpg",
    "title":"Portable Countertop Dishwashers, NOVETE Compact Dishwashers with 5 L Built-in Water",
    "deal":"deal",
    "discount":"27"
 }, 
 {
    "img":"https://i.ibb.co/YcvSwx8/41t-E5-JEopo-L-AC-UF226-226-FMjpg.jpg",
    "title":"VIVOHOME Electric Portable Compact Countertop Automatic Ice Cube Maker Machine with Hand Scoop and Self Cleaning Function",
    "deal":"deal",
    "discount":"25"
 }, 
 {
    "img":"https://i.ibb.co/fxCgg44/41-SSDW3e-G4-L-AC-UF226-226-FMjpg.jpg",
    "title":"Waterdrop DA97-17376B Replacement for Samsung HAF-QIN/EXP, DA97-08006C,",
    "deal":"deal",
    "discount":"28"
 }, 
 {
    "img":"https://i.ibb.co/D8dZ98g/41sjm-A2-Vs-AL-AC-UF226-226-FMjpg.jpg",
    "title":"Maxblue MB-F38 Water Filter",
    "deal":"deal",
    "discount":"36"
 }, 
 {
    "img":"https://i.ibb.co/JxtxHFb/41r0pc-LWJGL-AC-UF226-226-FMjpg.jpg",
    "title":"Maxblue Replacement for GE® RPWFE Refrigerator Water Filter 1&2",
    "deal":"deal",
    "discount":"38"
 }, 
 {
    "img":"https://i.ibb.co/TK48P0w/41kiakf-F1-L-AC-UF226-226-FMjpg.jpg",
    "title":"Kndko Nugget Ice Maker Countertop,34lbs/Day,Portable Crushed Ice Machine,Self Cleaning with One-Click Design ",
    "deal":"deal",
    "discount":"43"
 }, 
 {
    "img":"https://i.ibb.co/stVzR6f/41j-PTa17-OXL-AC-UF226-226-FMjpg.jpg",
    "title":"Save on Euhomy Compact Dryer 1.8 cu. ft. Portable Clothes Dryers with Exhaust Duct with",
    "deal":"deal",
    "discount":"45"
 }, 
 {
    "img":"https://i.ibb.co/N2pmNQw/41jb-Vdz2-Ho-L-AC-UF226-226-FMjpg.jpg",
    "title":"Mueller Ice Maker 2lbs",
    "deal":"deal",
    "discount":"43"
 }, 
 {
    "img":"https://i.ibb.co/MnQ01vy/41-IB-MBg-KL-AC-UF226-226-FMjpg.jpg",
    "title":"Electactic Ice Maker, Commercial Ice Machine,100Lbs/Day, Stainless Steel Ice",
    "deal":"deal",
    "discount":"35"
 }, 
 {
    "img":"https://i.ibb.co/0rb9HCm/41h3-Ne21a-VL-AC-UF226-226-FMjpg.jpg",
    "title":"Portable Ice Machine with ice Scoop and Basket,Bullet ice ice Bullet",
    "deal":"deal",
    "discount":"38"
 }, 
 {
    "img":"https://i.ibb.co/BgVhMVt/41fb-ZCsmh-L-AC-UF226-226-FMjpg.jpg",
    "title":"Waterdrop DA29-00020B Replacement for Samsung Water Filter HAF-CIN/EXP, DA29-00020B, HAF-CIN, DA29-00020B-1,",
    "deal":"deal",
    "discount":"46"
 }, 
 {
    "img":"https://i.ibb.co/59HjF7X/41-E-0-P-KH6-L-AC-UF226-226-FMjpg.jpg",
    "title":"Midea MDF18A1AST Built-in Dishwasher with 8 Place Settings, 6 Washing Programs, Stainless Steel Tub, Heated Dry, Energy Star",
    "deal":"deal",
    "discount":"49"
 }, 
 {
    "img":"https://i.ibb.co/D5hK8Vy/41dqsa-GQJ6-L-AC-UF226-226-FMjpg.jpg",
    "title":"Maxblue MB-F08 water filter",
    "deal":"deal",
    "discount":"50"
 }, 
 {
    "img":"https://i.ibb.co/7Y0sZdk/41da-I1-Gc-L-AC-UF226-226-FMjpg.jpg",
    "title":"EASYERA Nugget Ice Maker Countertop, Pellet Crushed Chewble Ice Cubes, 33LBS/24H, Compact Self-Cleaning Machine with Ice B",
    "deal":"deal",
    "discount":"18"
 }, 
 {
    "img":"https://i.ibb.co/2tj95FR/41b-Gh-RVOx-YL-AC-UF226-226-FMjpg.jpg",
    "title":"Euhomy 110V Portable Clothes Dryer 850W Compact Laundry Dryers 1.5 cu.ft Front Load",
    "deal":"deal",
    "discount":"28"
 }, 
 {
    "img":"https://i.ibb.co/cYVHphV/41-Vcq-Gymg-L-AC-UF226-226-FMjpg.jpg",
    "title":"Desktop Range Hood, Portable Range Hood with 2 Speed Exhaust Fan, Desktop Cooker Hood with Detachable Aluminum Filter, Large",
    "deal":"deal",
    "discount":"30"
 }, 
 {
    "img":"https://i.ibb.co/KyqKsRY/31-Xaoq-Ame4-L-AC-UF226-226-FMjpg.jpg",
    "title":"SNDOAS Black Range Hood 24/30/26 inch,Black",
    "deal":"deal",
    "discount":"31"
 }, 
 {
    "img":"https://i.ibb.co/grS7JFB/31-UHGe-Ra-TWL-AC-UF226-226-FMjpg.jpg",
    "title":"Crystala Filters Replacement for DA97-17376B Water Filter, NSF 42 Compatible with Samsung",
    "deal":"deal",
    "discount":"38"
 }, 
 {
    "img":"https://i.ibb.co/t3yZbFj/31qn3o-HDDn-L-AC-UF226-226-FMjpg.jpg",
    "title":"Euhomy Car Refrigerator",
    "deal":"deal",
    "discount":"11"
 }, 
 {
    "img":"https://i.ibb.co/hFK5YTH/31-MSBl1n-Ii-L-AC-UF226-226-FMjpg.jpg",
    "title":"MCBON Range Hood Insert,700 CFM Range Hood Insert, Ducted/Ductless Convertible Insert Range Hood, Vent Hood Insert, Stain",
    "deal":"deal",
    "discount":"16"
 }, 
 {
    "img":"https://i.ibb.co/cy2Rmb2/31l-YJhd4-Xl-L-AC-UF226-226-FMjpg.jpg",
    "title":"Comfee Range Hood",
    "deal":"deal",
    "discount":"33"
 }, 
 {
    "img":"https://i.ibb.co/Z1fy8B6/31k-6l-T7y-L-AC-UF226-226-FMjpg.jpg",
    "title":"Silonn Countertop Ice Maker, 45lbs Per Day, 24Pcs Ice Cubes in 13 Min, 2 Ways to Add",
    "deal":"deal",
    "discount":"48"
 }, 
 {
    "img":"https://i.ibb.co/z6k99rT/31-Fh-U-fjqt-L-AC-UF226-226-FMjpg.jpg",
    "title":"Anukis Compact Refrigerator 4.0 Cu Ft 2 Door Mini Fridge with Freezer For Apartment, Dorm, Office, Family, Basement, Garage",
    "deal":"deal",
    "discount":"50"
 }, 
 {
    "img":"https://i.ibb.co/8xQHFJ0/31dvc0j-O1-CL-AC-UF226-226-FMjpg.jpg",
    "title":"Ice Maker Countertop, Nugget Ice",
    "deal":"deal",
    "discount":"33"
 }, 
 {
    "img":"https://i.ibb.co/YdCwmQr/21-Rr-SOli4-L-AC-UF226-226-FMjpg.jpg",
    "title":"Karinear built-in size cook top",
    "deal":"deal",
    "discount":"45"
 },
 {
    "img":"",
    "title":"",
    "deal":"deal",
    "discount":""
 }

]


































